SubTextHighlight/Effects.py
SubTextHighlight/Highlight.py
SubTextHighlight/__init__.py
SubTextHighlight/handler.py
SubTextHighlight/main.py
SubTextHighlight/utils.py
SubTextHighlight/whisper_.py
SubTextHighlight/docker_wrapper/__init__.py
SubTextHighlight/docker_wrapper/base.py
SubTextHighlight/docker_wrapper/container.py
SubTextHighlight/docker_wrapper/main.py
subtexthighlight-2.1.dist-info/licenses/LICENSE
tests/test_docker.py
tests/test_subtitles.py
subtexthighlight-2.1.dist-info/METADATA
subtexthighlight-2.1.dist-info/WHEEL
subtexthighlight-2.1.dist-info/top_level.txt
subtexthighlight-2.1.dist-info/RECORD
