Metadata-Version: 2.4
Name: SubTextHighlight
Version: 2.1
Summary: This is a Package for generating and formatting subtitles while focusing on user-friendliness and providing many features.
License-Expression: GPL-3.0-only
Project-URL: Repository, https://github.com/kalterBebapKacke/SubTextHighlight.git
Keywords: subtitles
Requires-Python: >=3.13
License-File: LICENSE
Requires-Dist: pysubs2>=1.8.0
Requires-Dist: Cython>=3.1.1
Requires-Dist: openai-whisper>=20240930
Requires-Dist: stable-ts-whisperless>=2.19.0
Requires-Dist: fleep>=1.0.1
Requires-Dist: docker>=7.1.0
Dynamic: license-file
